zoom_client/__init__.py
zoom_client/cleint.py
zoom_client/client.py
Zoom_py_client-1.0.1.dist-info/METADATA
Zoom_py_client-1.0.1.dist-info/WHEEL
Zoom_py_client-1.0.1.dist-info/top_level.txt
Zoom_py_client-1.0.1.dist-info/RECORD
